COPYING
MANIFEST.in
README.rst
bootstrap.py
buildout.cfg
setup.py
docs/DIR.png
docs/conf.py
docs/index.rst
docs/scores.txt
xbob/__init__.py
xbob.measure.idmeasure.egg-info/PKG-INFO
xbob.measure.idmeasure.egg-info/SOURCES.txt
xbob.measure.idmeasure.egg-info/dependency_links.txt
xbob.measure.idmeasure.egg-info/entry_points.txt
xbob.measure.idmeasure.egg-info/requires.txt
xbob.measure.idmeasure.egg-info/top_level.txt
xbob.measure.idmeasure.egg-info/zip-safe
xbob/measure/__init__.py
xbob/measure/idmeasure/__init__.py
xbob/measure/idmeasure/idmeasure.py
xbob/measure/idmeasure/test_error.py