Metadata-Version: 1.0
Name: xbob.measure.idmeasure
Version: 0.0.3
Summary: Detection and Identification Rate
Home-page: http://pypi.python.org/pypi/xbob.measure.IDmeasure
Author: Chi Ho CHAN
Author-email: chiho.chan@surrey.ac.uk
License: GPLv3
Platform: UNKNOWN
